{"nodes": [{"type": "I", "text": "I: 0", "nodeID": "0", "text_occ_idx": 0}, {"type": "I", "text": "I: 1", "nodeID": "1", "text_occ_idx": 11}, {"type": "I", "text": "I: 2", "nodeID": "2", "text_occ_idx": 31}, {"type": "I", "text": "I: 3", "nodeID": "3", "text_occ_idx": 59}, {"type": "I", "text": "I: 4", "nodeID": "4", "text_occ_idx": 85}, {"type": "I", "text": "I: 5", "nodeID": "5", "text_occ_idx": 117}, {"type": "I", "text": "I: 6", "nodeID": "6", "text_occ_idx": 163}, {"type": "MA", "text": "Default Rephrase", "nodeID": "7"}, {"type": "CA", "text": "Default Conflict", "nodeID": "8"}, {"type": "CA", "text": "Default Conflict", "nodeID": "9"}, {"type": "MA", "text": "Default Rephrase", "nodeID": "10"}, {"type": "CA", "text": "Default Conflict", "nodeID": "11"}, {"type": "RA", "text": "Default Inference", "nodeID": "12"}, {"type": "I", "text": "I: 13", "nodeID": "13", "text_occ_idx": 13}, {"type": "I", "text": "I: 14", "nodeID": "14", "text_occ_idx": 33}, {"type": "I", "text": "I: 15", "nodeID": "15", "text_occ_idx": 61}, {"type": "I", "text": "I: 16", "nodeID": "16", "text_occ_idx": 87}, {"type": "I", "text": "I: 17", "nodeID": "17", "text_occ_idx": 127}, {"type": "I", "text": "I: 18", "nodeID": "18", "text_occ_idx": 181}, {"type": "MA", "text": "Default Rephrase", "nodeID": "19"}, {"type": "RA", "text": "Default Inference", "nodeID": "20"}, {"type": "RA", "text": "Default Inference", "nodeID": "21"}, {"type": "CA", "text": "Default Conflict", "nodeID": "22"}, {"type": "CA", "text": "Default Conflict", "nodeID": "23"}, {"nodeID": "24", "text": "Default Inference", "type": "RA"}, {"nodeID": "25", "type": "I", "text": "I: 25 -> Leaf;", "text_occ_idx": 245}, {"nodeID": "26", "type": "CA", "text": "Default Conflict"}, {"nodeID": "27", "type": "I", "text": "I: 27 -> Leaf;", "text_occ_idx": 247}, {"nodeID": "28", "type": "RA", "text": "Default Inference"}, {"nodeID": "29", "type": "I", "text": "I: 29 -> Leaf;", "text_occ_idx": 249}, {"nodeID": "30", "type": "MA", "text": "Default Rephrase"}, {"nodeID": "31", "type": "I", "text": "I: 31 -> Leaf;", "text_occ_idx": 251}, {"nodeID": "32", "type": "RA", "text": "Default Inference"}, {"nodeID": "33", "type": "I", "text": "I: 33 -> Leaf;", "text_occ_idx": 253}, {"nodeID": "34", "type": "MA", "text": "Default Rephrase"}, {"type": "I", "text": "I: 35", "nodeID": "35", "text_occ_idx": 15}, {"type": "I", "text": "I: 36", "nodeID": "36", "text_occ_idx": 35}, {"type": "I", "text": "I: 37", "nodeID": "37", "text_occ_idx": 63}, {"type": "I", "text": "I: 38", "nodeID": "38", "text_occ_idx": 89}, {"type": "I", "text": "I: 39", "nodeID": "39", "text_occ_idx": 129}, {"type": "I", "text": "I: 40", "nodeID": "40", "text_occ_idx": 183}, {"type": "CA", "text": "Default Conflict", "nodeID": "41"}, {"type": "CA", "text": "Default Conflict", "nodeID": "42"}, {"type": "CA", "text": "Default Conflict", "nodeID": "43"}, {"type": "CA", "text": "Default Conflict", "nodeID": "44"}, {"type": "CA", "text": "Default Conflict", "nodeID": "45"}, {"nodeID": "46", "text": "Default Conflict", "type": "CA"}, {"nodeID": "47", "type": "I", "text": "I: 47 -> Leaf;", "text_occ_idx": 255}, {"nodeID": "48", "type": "RA", "text": "Default Inference"}, {"nodeID": "49", "type": "I", "text": "I: 49 -> Leaf;", "text_occ_idx": 257}, {"nodeID": "50", "type": "RA", "text": "Default Inference"}, {"nodeID": "51", "type": "I", "text": "I: 51 -> Leaf;", "text_occ_idx": 259}, {"nodeID": "52", "type": "MA", "text": "Default Rephrase"}, {"type": "I", "text": "I: 53", "nodeID": "53", "text_occ_idx": 17}, {"type": "I", "text": "I: 54", "nodeID": "54", "text_occ_idx": 37}, {"type": "I", "text": "I: 55", "nodeID": "55", "text_occ_idx": 65}, {"type": "I", "text": "I: 56", "nodeID": "56", "text_occ_idx": 91}, {"type": "RA", "text": "Default Inference", "nodeID": "57"}, {"type": "MA", "text": "Default Rephrase", "nodeID": "58"}, {"type": "CA", "text": "Default Conflict", "nodeID": "59"}, {"nodeID": "60", "text": "Default Rephrase", "type": "MA"}, {"nodeID": "61", "type": "I", "text": "I: 61 -> Leaf;", "text_occ_idx": 131}, {"nodeID": "62", "type": "MA", "text": "Default Rephrase"}, {"nodeID": "63", "type": "I", "text": "I: 63 -> Leaf;", "text_occ_idx": 133}, {"nodeID": "64", "type": "MA", "text": "Default Rephrase"}, {"nodeID": "65", "type": "I", "text": "I: 65 -> Leaf;", "text_occ_idx": 135}, {"nodeID": "66", "type": "MA", "text": "Default Rephrase"}, {"nodeID": "67", "type": "I", "text": "I: 67 -> Leaf;", "text_occ_idx": 137}, {"nodeID": "68", "type": "CA", "text": "Default Conflict"}, {"nodeID": "69", "type": "I", "text": "I: 69 -> Leaf;", "text_occ_idx": 139}, {"nodeID": "70", "type": "RA", "text": "Default Inference"}, {"type": "I", "text": "I: 71", "nodeID": "71", "text_occ_idx": 19}, {"type": "I", "text": "I: 72", "nodeID": "72", "text_occ_idx": 39}, {"type": "MA", "text": "Default Rephrase", "nodeID": "73"}, {"nodeID": "74", "text": "Default Inference", "type": "RA"}, {"nodeID": "75", "type": "I", "text": "I: 75 -> Leaf;", "text_occ_idx": 67}, {"nodeID": "76", "type": "RA", "text": "Default Inference"}, {"nodeID": "77", "type": "I", "text": "I: 77 -> Leaf;", "text_occ_idx": 69}, {"nodeID": "78", "type": "RA", "text": "Default Inference"}, {"nodeID": "79", "type": "I", "text": "I: 79 -> Leaf;", "text_occ_idx": 71}, {"nodeID": "80", "type": "CA", "text": "Default Conflict"}, {"nodeID": "81", "type": "I", "text": "I: 81 -> Leaf;", "text_occ_idx": 73}, {"nodeID": "82", "type": "RA", "text": "Default Inference"}, {"nodeID": "83", "type": "I", "text": "I: 83 -> Leaf;", "text_occ_idx": 75}, {"nodeID": "84", "type": "CA", "text": "Default Conflict"}, {"type": "I", "text": "I: 85", "nodeID": "85", "text_occ_idx": 119}, {"type": "I", "text": "I: 86", "nodeID": "86", "text_occ_idx": 173}, {"type": "I", "text": "I: 87", "nodeID": "87", "text_occ_idx": 237}, {"type": "CA", "text": "Default Conflict", "nodeID": "88"}, {"type": "CA", "text": "Default Conflict", "nodeID": "89"}, {"nodeID": "90", "text": "Default Rephrase", "type": "MA"}, {"nodeID": "91", "type": "I", "text": "I: 91 -> Leaf;", "text_occ_idx": 329}, {"nodeID": "92", "type": "RA", "text": "Default Inference"}, {"nodeID": "93", "type": "I", "text": "I: 93 -> Leaf;", "text_occ_idx": 331}, {"nodeID": "94", "type": "CA", "text": "Default Conflict"}, {"nodeID": "95", "type": "I", "text": "I: 95 -> Leaf;", "text_occ_idx": 333}, {"nodeID": "96", "type": "CA", "text": "Default Conflict"}, {"type": "I", "text": "I: 97", "nodeID": "97", "text_occ_idx": 121}, {"type": "I", "text": "I: 98", "nodeID": "98", "text_occ_idx": 175}, {"type": "I", "text": "I: 99", "nodeID": "99", "text_occ_idx": 239}, {"type": "I", "text": "I: 100", "nodeID": "100", "text_occ_idx": 335}, {"type": "MA", "text": "Default Rephrase", "nodeID": "101"}, {"type": "RA", "text": "Default Inference", "nodeID": "102"}, {"type": "CA", "text": "Default Conflict", "nodeID": "103"}, {"nodeID": "104", "text": "Default Conflict", "type": "CA"}, {"nodeID": "105", "type": "I", "text": "I: 105 -> Leaf;", "text_occ_idx": 407}, {"nodeID": "106", "type": "CA", "text": "Default Conflict"}, {"nodeID": "107", "type": "I", "text": "I: 107 -> Leaf;", "text_occ_idx": 409}, {"nodeID": "108", "type": "MA", "text": "Default Rephrase"}, {"nodeID": "109", "type": "I", "text": "I: 109 -> Leaf;", "text_occ_idx": 411}, {"nodeID": "110", "type": "CA", "text": "Default Conflict"}, {"nodeID": "111", "type": "I", "text": "I: 111 -> Leaf;", "text_occ_idx": 413}, {"nodeID": "112", "type": "RA", "text": "Default Inference"}, {"type": "I", "text": "I: 113", "nodeID": "113", "text_occ_idx": 123}, {"type": "I", "text": "I: 114", "nodeID": "114", "text_occ_idx": 177}, {"type": "I", "text": "I: 115", "nodeID": "115", "text_occ_idx": 241}, {"type": "I", "text": "I: 116", "nodeID": "116", "text_occ_idx": 337}, {"type": "MA", "text": "Default Rephrase", "nodeID": "117"}, {"type": "RA", "text": "Default Inference", "nodeID": "118"}, {"type": "CA", "text": "Default Conflict", "nodeID": "119"}, {"nodeID": "120", "text": "Default Conflict", "type": "CA"}, {"nodeID": "121", "type": "I", "text": "I: 121 -> Leaf;", "text_occ_idx": 415}, {"nodeID": "122", "type": "MA", "text": "Default Rephrase"}, {"nodeID": "123", "type": "I", "text": "I: 123 -> Leaf;", "text_occ_idx": 417}, {"nodeID": "124", "type": "RA", "text": "Default Inference"}, {"nodeID": "125", "type": "I", "text": "I: 125 -> Leaf;", "text_occ_idx": 419}, {"nodeID": "126", "type": "RA", "text": "Default Inference"}, {"type": "I", "text": "I: 127", "nodeID": "127", "text_occ_idx": 125}, {"type": "I", "text": "I: 128", "nodeID": "128", "text_occ_idx": 179}, {"type": "I", "text": "I: 129", "nodeID": "129", "text_occ_idx": 243}, {"type": "CA", "text": "Default Conflict", "nodeID": "130"}, {"type": "RA", "text": "Default Inference", "nodeID": "131"}, {"nodeID": "132", "text": "Default Rephrase", "type": "MA"}, {"nodeID": "133", "type": "I", "text": "I: 133 -> Leaf;", "text_occ_idx": 339}, {"nodeID": "134", "type": "MA", "text": "Default Rephrase"}, {"nodeID": "135", "type": "I", "text": "I: 135 -> Leaf;", "text_occ_idx": 341}, {"nodeID": "136", "type": "MA", "text": "Default Rephrase"}, {"nodeID": "137", "type": "I", "text": "I: 137 -> Leaf;", "text_occ_idx": 343}, {"nodeID": "138", "type": "MA", "text": "Default Rephrase"}, {"nodeID": "139", "type": "I", "text": "I: 139 -> Leaf;", "text_occ_idx": 345}, {"nodeID": "140", "type": "MA", "text": "Default Rephrase"}, {"nodeID": "141", "type": "I", "text": "I: 141 -> Leaf;", "text_occ_idx": 347}, {"nodeID": "142", "type": "MA", "text": "Default Rephrase"}, {"type": "I", "text": "I: 143", "nodeID": "143", "text_occ_idx": 165}, {"type": "I", "text": "I: 144", "nodeID": "144", "text_occ_idx": 229}, {"type": "I", "text": "I: 145", "nodeID": "145", "text_occ_idx": 311}, {"type": "I", "text": "I: 146", "nodeID": "146", "text_occ_idx": 401}, {"type": "I", "text": "I: 147", "nodeID": "147", "text_occ_idx": 439}, {"type": "RA", "text": "Default Inference", "nodeID": "148"}, {"type": "CA", "text": "Default Conflict", "nodeID": "149"}, {"type": "MA", "text": "Default Rephrase", "nodeID": "150"}, {"type": "RA", "text": "Default Inference", "nodeID": "151"}, {"nodeID": "152", "text": "Default Conflict", "type": "CA"}, {"nodeID": "153", "type": "I", "text": "I: 153 -> Leaf;", "text_occ_idx": 447}, {"nodeID": "154", "type": "CA", "text": "Default Conflict"}, {"nodeID": "155", "type": "I", "text": "I: 155 -> Leaf;", "text_occ_idx": 449}, {"nodeID": "156", "type": "MA", "text": "Default Rephrase"}, {"nodeID": "157", "type": "I", "text": "I: 157 -> Leaf;", "text_occ_idx": 451}, {"nodeID": "158", "type": "RA", "text": "Default Inference"}, {"type": "I", "text": "I: 159", "nodeID": "159", "text_occ_idx": 167}, {"type": "I", "text": "I: 160", "nodeID": "160", "text_occ_idx": 231}, {"type": "MA", "text": "Default Rephrase", "nodeID": "161"}, {"nodeID": "162", "text": "Default Inference", "type": "RA"}, {"nodeID": "163", "type": "I", "text": "I: 163 -> Leaf;", "text_occ_idx": 313}, {"nodeID": "164", "type": "MA", "text": "Default Rephrase"}, {"nodeID": "165", "type": "I", "text": "I: 165 -> Leaf;", "text_occ_idx": 315}, {"nodeID": "166", "type": "RA", "text": "Default Inference"}, {"nodeID": "167", "type": "I", "text": "I: 167 -> Leaf;", "text_occ_idx": 317}, {"nodeID": "168", "type": "CA", "text": "Default Conflict"}, {"type": "I", "text": "I: 169", "nodeID": "169", "text_occ_idx": 169}, {"type": "I", "text": "I: 170", "nodeID": "170", "text_occ_idx": 233}, {"type": "RA", "text": "Default Inference", "nodeID": "171"}, {"nodeID": "172", "text": "Default Conflict", "type": "CA"}, {"nodeID": "173", "type": "I", "text": "I: 173 -> Leaf;", "text_occ_idx": 319}, {"nodeID": "174", "type": "MA", "text": "Default Rephrase"}, {"nodeID": "175", "type": "I", "text": "I: 175 -> Leaf;", "text_occ_idx": 321}, {"nodeID": "176", "type": "MA", "text": "Default Rephrase"}, {"nodeID": "177", "type": "I", "text": "I: 177 -> Leaf;", "text_occ_idx": 323}, {"nodeID": "178", "type": "RA", "text": "Default Inference"}, {"nodeID": "179", "type": "I", "text": "I: 179 -> Leaf;", "text_occ_idx": 325}, {"nodeID": "180", "type": "CA", "text": "Default Conflict"}, {"type": "I", "text": "I: 181", "nodeID": "181", "text_occ_idx": 171}, {"type": "I", "text": "I: 182", "nodeID": "182", "text_occ_idx": 235}, {"type": "I", "text": "I: 183", "nodeID": "183", "text_occ_idx": 327}, {"type": "CA", "text": "Default Conflict", "nodeID": "184"}, {"type": "MA", "text": "Default Rephrase", "nodeID": "185"}, {"nodeID": "186", "text": "Default Conflict", "type": "CA"}, {"nodeID": "187", "type": "I", "text": "I: 187 -> Leaf;", "text_occ_idx": 403}, {"nodeID": "188", "type": "CA", "text": "Default Conflict"}, {"nodeID": "189", "type": "I", "text": "I: 189 -> Leaf;", "text_occ_idx": 405}, {"nodeID": "190", "type": "MA", "text": "Default Rephrase"}, {"type": "I", "text": "I: 191", "nodeID": "191", "text_occ_idx": 223}, {"type": "I", "text": "I: 192", "nodeID": "192", "text_occ_idx": 305}, {"type": "MA", "text": "Default Rephrase", "nodeID": "193"}, {"nodeID": "194", "text": "Default Rephrase", "type": "MA"}, {"nodeID": "195", "type": "I", "text": "I: 195 -> Leaf;", "text_occ_idx": 385}, {"nodeID": "196", "type": "RA", "text": "Default Inference"}, {"nodeID": "197", "type": "I", "text": "I: 197 -> Leaf;", "text_occ_idx": 387}, {"nodeID": "198", "type": "MA", "text": "Default Rephrase"}, {"type": "I", "text": "I: 199", "nodeID": "199", "text_occ_idx": 225}, {"type": "I", "text": "I: 200", "nodeID": "200", "text_occ_idx": 307}, {"type": "CA", "text": "Default Conflict", "nodeID": "201"}, {"nodeID": "202", "text": "Default Rephrase", "type": "MA"}, {"nodeID": "203", "type": "I", "text": "I: 203 -> Leaf;", "text_occ_idx": 389}, {"nodeID": "204", "type": "MA", "text": "Default Rephrase"}, {"nodeID": "205", "type": "I", "text": "I: 205 -> Leaf;", "text_occ_idx": 391}, {"nodeID": "206", "type": "CA", "text": "Default Conflict"}, {"nodeID": "207", "type": "I", "text": "I: 207 -> Leaf;", "text_occ_idx": 393}, {"nodeID": "208", "type": "MA", "text": "Default Rephrase"}, {"nodeID": "209", "type": "I", "text": "I: 209 -> Leaf;", "text_occ_idx": 395}, {"nodeID": "210", "type": "MA", "text": "Default Rephrase"}, {"nodeID": "211", "type": "I", "text": "I: 211 -> Leaf;", "text_occ_idx": 397}, {"nodeID": "212", "type": "CA", "text": "Default Conflict"}, {"type": "I", "text": "I: 213", "nodeID": "213", "text_occ_idx": 227}, {"type": "I", "text": "I: 214", "nodeID": "214", "text_occ_idx": 309}, {"type": "I", "text": "I: 215", "nodeID": "215", "text_occ_idx": 399}, {"type": "MA", "text": "Default Rephrase", "nodeID": "216"}, {"type": "CA", "text": "Default Conflict", "nodeID": "217"}, {"nodeID": "218", "text": "Default Conflict", "type": "CA"}, {"nodeID": "219", "type": "I", "text": "I: 219 -> Leaf;", "text_occ_idx": 431}, {"nodeID": "220", "type": "CA", "text": "Default Conflict"}, {"nodeID": "221", "type": "I", "text": "I: 221 -> Leaf;", "text_occ_idx": 433}, {"nodeID": "222", "type": "CA", "text": "Default Conflict"}, {"nodeID": "223", "type": "I", "text": "I: 223 -> Leaf;", "text_occ_idx": 435}, {"nodeID": "224", "type": "MA", "text": "Default Rephrase"}, {"nodeID": "225", "type": "I", "text": "I: 225 -> Leaf;", "text_occ_idx": 437}, {"nodeID": "226", "type": "MA", "text": "Default Rephrase"}, {"type": "YA", "nodeID": "227", "text": "Pure Questioning"}, {"type": "YA", "nodeID": "228", "text": "Rhetorical Questioning"}, {"type": "YA", "nodeID": "229", "text": "Pure Questioning"}, {"type": "YA", "nodeID": "230", "text": "Disagreeing"}, {"type": "YA", "nodeID": "231", "text": "Rhetorical Questioning"}, {"type": "YA", "nodeID": "232", "text": "Agreeing"}, {"type": "YA", "nodeID": "233", "text": "Rhetorical Questioning"}, {"type": "YA", "nodeID": "234", "text": "Default Illocuting"}, {"type": "YA", "nodeID": "235", "text": "Disagreeing"}, {"type": "YA", "nodeID": "236", "text": "Disagreeing"}, {"type": "YA", "nodeID": "237", "text": "Restating"}, {"type": "YA", "nodeID": "238", "text": "Disagreeing"}, {"type": "YA", "nodeID": "239", "text": "Arguing"}, {"type": "YA", "nodeID": "240", "text": "Disagreeing"}, {"type": "YA", "nodeID": "241", "text": "Rhetorical Questioning"}, {"type": "YA", "nodeID": "242", "text": "Pure Questioning"}, {"type": "YA", "nodeID": "243", "text": "Asserting"}, {"type": "YA", "nodeID": "244", "text": "Pure Questioning"}, {"type": "YA", "nodeID": "245", "text": "Asserting"}, {"type": "YA", "nodeID": "246", "text": "Restating"}, {"type": "YA", "nodeID": "247", "text": "Arguing"}, {"type": "YA", "nodeID": "248", "text": "Arguing"}, {"type": "YA", "nodeID": "249", "text": "Disagreeing"}, {"type": "YA", "nodeID": "250", "text": "Disagreeing"}, {"type": "YA", "nodeID": "251", "text": "Arguing"}, {"type": "YA", "nodeID": "252", "text": "Disagreeing"}, {"type": "YA", "nodeID": "253", "text": "Disagreeing"}, {"type": "YA", "nodeID": "254", "text": "Asserting"}, {"type": "YA", "nodeID": "255", "text": "Arguing"}, {"type": "YA", "nodeID": "256", "text": "Pure Questioning"}, {"type": "YA", "nodeID": "257", "text": "Default Illocuting"}, {"type": "YA", "nodeID": "258", "text": "Agreeing"}, {"type": "YA", "nodeID": "259", "text": "Arguing"}, {"type": "YA", "nodeID": "260", "text": "Agreeing"}, {"type": "YA", "nodeID": "261", "text": "Default Illocuting"}, {"type": "YA", "nodeID": "262", "text": "Pure Questioning"}, {"type": "YA", "nodeID": "263", "text": "Asserting"}, {"type": "YA", "nodeID": "264", "text": "Asserting"}, {"type": "YA", "nodeID": "265", "text": "Rhetorical Questioning"}, {"type": "YA", "nodeID": "266", "text": "Rhetorical Questioning"}, {"type": "YA", "nodeID": "267", "text": "Asserting"}, {"type": "YA", "nodeID": "268", "text": "Disagreeing"}, {"type": "YA", "nodeID": "269", "text": "Disagreeing"}, {"type": "YA", "nodeID": "270", "text": "Disagreeing"}, {"type": "YA", "nodeID": "271", "text": "Disagreeing"}, {"type": "YA", "nodeID": "272", "text": "Disagreeing"}, {"type": "YA", "nodeID": "273", "text": "Disagreeing"}, {"type": "YA", "nodeID": "274", "text": "Asserting"}, {"type": "YA", "nodeID": "275", "text": "Arguing"}, {"type": "YA", "nodeID": "276", "text": "Agreeing"}, {"type": "YA", "nodeID": "277", "text": "Arguing"}, {"type": "YA", "nodeID": "278", "text": "Disagreeing"}, {"type": "YA", "nodeID": "279", "text": "Default Illocuting"}, {"type": "YA", "nodeID": "280", "text": "Agreeing"}, {"type": "YA", "nodeID": "281", "text": "Rhetorical Questioning"}, {"type": "YA", "nodeID": "282", "text": "Asserting"}, {"type": "YA", "nodeID": "283", "text": "Disagreeing"}, {"type": "YA", "nodeID": "284", "text": "Arguing"}, {"type": "YA", "nodeID": "285", "text": "Restating"}, {"type": "YA", "nodeID": "286", "text": "Disagreeing"}, {"type": "YA", "nodeID": "287", "text": "Restating"}, {"type": "YA", "nodeID": "288", "text": "Disagreeing"}, {"type": "YA", "nodeID": "289", "text": "Default Illocuting"}, {"type": "YA", "nodeID": "290", "text": "Pure Questioning"}, {"type": "YA", "nodeID": "291", "text": "Default Illocuting"}, {"type": "YA", "nodeID": "292", "text": "Asserting"}, {"type": "YA", "nodeID": "293", "text": "Default Illocuting"}, {"type": "YA", "nodeID": "294", "text": "Pure Questioning"}, {"type": "YA", "nodeID": "295", "text": "Disagreeing"}, {"type": "YA", "nodeID": "296", "text": "Rhetorical Questioning"}, {"type": "YA", "nodeID": "297", "text": "Arguing"}, {"type": "YA", "nodeID": "298", "text": "Asserting"}, {"type": "YA", "nodeID": "299", "text": "Disagreeing"}, {"type": "YA", "nodeID": "300", "text": "Restating"}, {"type": "YA", "nodeID": "301", "text": "Arguing"}, {"type": "YA", "nodeID": "302", "text": "Rhetorical Questioning"}, {"type": "YA", "nodeID": "303", "text": "Arguing"}, {"type": "YA", "nodeID": "304", "text": "Asserting"}, {"type": "YA", "nodeID": "305", "text": "Arguing"}, {"type": "YA", "nodeID": "306", "text": "Disagreeing"}, {"type": "YA", "nodeID": "307", "text": "Disagreeing"}, {"type": "YA", "nodeID": "308", "text": "Agreeing"}, {"type": "YA", "nodeID": "309", "text": "Arguing"}, {"type": "YA", "nodeID": "310", "text": "Agreeing"}, {"type": "YA", "nodeID": "311", "text": "Disagreeing"}, {"type": "YA", "nodeID": "312", "text": "Pure Questioning"}, {"type": "YA", "nodeID": "313", "text": "Pure Questioning"}, {"type": "YA", "nodeID": "314", "text": "Pure Questioning"}, {"type": "YA", "nodeID": "315", "text": "Disagreeing"}, {"type": "YA", "nodeID": "316", "text": "Disagreeing"}, {"type": "YA", "nodeID": "317", "text": "Default Illocuting"}, {"type": "YA", "nodeID": "318", "text": "Agreeing"}, {"type": "YA", "nodeID": "319", "text": "Arguing"}, {"type": "YA", "nodeID": "320", "text": "Asserting"}, {"type": "YA", "nodeID": "321", "text": "Disagreeing"}, {"type": "YA", "nodeID": "322", "text": "Disagreeing"}, {"type": "YA", "nodeID": "323", "text": "Disagreeing"}, {"type": "YA", "nodeID": "324", "text": "Rhetorical Questioning"}, {"type": "YA", "nodeID": "325", "text": "Disagreeing"}, {"type": "YA", "nodeID": "326", "text": "Disagreeing"}, {"type": "YA", "nodeID": "327", "text": "Pure Questioning"}, {"type": "YA", "nodeID": "328", "text": "Restating"}, {"type": "YA", "nodeID": "329", "text": "Arguing"}, {"type": "YA", "nodeID": "330", "text": "Disagreeing"}, {"type": "YA", "nodeID": "331", "text": "Disagreeing"}, {"type": "YA", "nodeID": "332", "text": "Agreeing"}, {"type": "YA", "nodeID": "333", "text": "Disagreeing"}, {"type": "YA", "nodeID": "334", "text": "Agreeing"}, {"type": "YA", "nodeID": "335", "text": "Restating"}, {"type": "YA", "nodeID": "336", "text": "Rhetorical Questioning"}, {"type": "YA", "nodeID": "337", "text": "Disagreeing"}, {"type": "YA", "nodeID": "338", "text": "Disagreeing"}, {"type": "YA", "nodeID": "339", "text": "Arguing"}, {"type": "YA", "nodeID": "340", "text": "Pure Questioning"}, {"type": "YA", "nodeID": "341", "text": "Agreeing"}, {"type": "YA", "nodeID": "342", "text": "Pure Questioning"}, {"type": "YA", "nodeID": "343", "text": "Agreeing"}, {"type": "YA", "nodeID": "344", "text": "Default Illocuting"}, {"type": "YA", "nodeID": "345", "text": "Arguing"}, {"type": "YA", "nodeID": "346", "text": "Disagreeing"}, {"type": "YA", "nodeID": "347", "text": "Disagreeing"}, {"type": "YA", "nodeID": "348", "text": "Agreeing"}, {"type": "YA", "nodeID": "349", "text": "Default Illocuting"}, {"type": "YA", "nodeID": "350", "text": "Agreeing"}, {"type": "YA", "nodeID": "351", "text": "Arguing"}, {"type": "YA", "nodeID": "352", "text": "Rhetorical Questioning"}, {"type": "YA", "nodeID": "353", "text": "Arguing"}, {"type": "YA", "nodeID": "354", "text": "Disagreeing"}, {"type": "YA", "nodeID": "355", "text": "Pure Questioning"}, {"type": "YA", "nodeID": "356", "text": "Agreeing"}, {"type": "YA", "nodeID": "357", "text": "Disagreeing"}, {"type": "YA", "nodeID": "358", "text": "Arguing"}, {"type": "YA", "nodeID": "359", "text": "Default Illocuting"}, {"type": "YA", "nodeID": "360", "text": "Agreeing"}, {"type": "YA", "nodeID": "361", "text": "Restating"}, {"type": "YA", "nodeID": "362", "text": "Disagreeing"}, {"type": "YA", "nodeID": "363", "text": "Default Illocuting"}, {"type": "YA", "nodeID": "364", "text": "Agreeing"}, {"type": "YA", "nodeID": "365", "text": "Default Illocuting"}, {"type": "YA", "nodeID": "366", "text": "Agreeing"}, {"type": "YA", "nodeID": "367", "text": "Default Illocuting"}, {"type": "YA", "nodeID": "368", "text": "Asserting"}, {"type": "YA", "nodeID": "369", "text": "Default Illocuting"}, {"type": "YA", "nodeID": "370", "text": "Disagreeing"}, {"type": "YA", "nodeID": "371", "text": "Asserting"}, {"type": "YA", "nodeID": "372", "text": "Pure Questioning"}, {"type": "YA", "nodeID": "373", "text": "Pure Questioning"}, {"type": "YA", "nodeID": "374", "text": "Rhetorical Questioning"}, {"type": "YA", "nodeID": "375", "text": "Arguing"}, {"type": "YA", "nodeID": "376", "text": "Disagreeing"}, {"type": "YA", "nodeID": "377", "text": "Restating"}, {"type": "YA", "nodeID": "378", "text": "Arguing"}, {"type": "YA", "nodeID": "379", "text": "Disagreeing"}, {"type": "YA", "nodeID": "380", "text": "Disagreeing"}, {"type": "YA", "nodeID": "381", "text": "Disagreeing"}, {"type": "YA", "nodeID": "382", "text": "Rhetorical Questioning"}, {"type": "YA", "nodeID": "383", "text": "Restating"}, {"type": "YA", "nodeID": "384", "text": "Pure Questioning"}, {"type": "YA", "nodeID": "385", "text": "Arguing"}, {"type": "YA", "nodeID": "386", "text": "Pure Questioning"}, {"type": "YA", "nodeID": "387", "text": "Asserting"}, {"type": "YA", "nodeID": "388", "text": "Restating"}, {"type": "YA", "nodeID": "389", "text": "Arguing"}, {"type": "YA", "nodeID": "390", "text": "Pure Questioning"}, {"type": "YA", "nodeID": "391", "text": "Restating"}, {"type": "YA", "nodeID": "392", "text": "Agreeing"}, {"type": "YA", "nodeID": "393", "text": "Arguing"}, {"type": "YA", "nodeID": "394", "text": "Disagreeing"}, {"type": "YA", "nodeID": "395", "text": "Disagreeing"}, {"type": "YA", "nodeID": "396", "text": "Asserting"}, {"type": "YA", "nodeID": "397", "text": "Pure Questioning"}, {"type": "YA", "nodeID": "398", "text": "Arguing"}, {"type": "YA", "nodeID": "399", "text": "Disagreeing"}, {"type": "YA", "nodeID": "400", "text": "Pure Questioning"}, {"type": "YA", "nodeID": "401", "text": "Restating"}, {"type": "YA", "nodeID": "402", "text": "Pure Questioning"}, {"type": "YA", "nodeID": "403", "text": "Restating"}, {"type": "YA", "nodeID": "404", "text": "Agreeing"}, {"type": "YA", "nodeID": "405", "text": "Arguing"}, {"type": "YA", "nodeID": "406", "text": "Pure Questioning"}, {"type": "YA", "nodeID": "407", "text": "Disagreeing"}, {"type": "YA", "nodeID": "408", "text": "Pure Questioning"}, {"type": "YA", "nodeID": "409", "text": "Asserting"}, {"type": "YA", "nodeID": "410", "text": "Agreeing"}, {"type": "YA", "nodeID": "411", "text": "Disagreeing"}, {"type": "YA", "nodeID": "412", "text": "Default Illocuting"}, {"type": "YA", "nodeID": "413", "text": "Disagreeing"}, {"type": "YA", "nodeID": "414", "text": "Asserting"}, {"type": "YA", "nodeID": "415", "text": "Disagreeing"}, {"type": "YA", "nodeID": "416", "text": "Asserting"}, {"type": "YA", "nodeID": "417", "text": "Default Illocuting"}, {"type": "YA", "nodeID": "418", "text": "Pure Questioning"}, {"type": "YA", "nodeID": "419", "text": "Asserting"}, {"type": "YA", "nodeID": "420", "text": "Default Illocuting"}, {"type": "YA", "nodeID": "421", "text": "Default Illocuting"}, {"type": "YA", "nodeID": "422", "text": "Pure Questioning"}, {"type": "YA", "nodeID": "423", "text": "Arguing"}, {"type": "YA", "nodeID": "424", "text": "Asserting"}, {"type": "YA", "nodeID": "425", "text": "Default Illocuting"}, {"type": "YA", "nodeID": "426", "text": "Asserting"}, {"type": "YA", "nodeID": "427", "text": "Asserting"}, {"type": "YA", "nodeID": "428", "text": "Disagreeing"}, {"type": "YA", "nodeID": "429", "text": "Default Illocuting"}, {"type": "YA", "nodeID": "430", "text": "Rhetorical Questioning"}, {"type": "YA", "nodeID": "431", "text": "Default Illocuting"}, {"type": "YA", "nodeID": "432", "text": "Rhetorical Questioning"}, {"type": "YA", "nodeID": "433", "text": "Disagreeing"}, {"type": "YA", "nodeID": "434", "text": "Pure Questioning"}, {"type": "YA", "nodeID": "435", "text": "Restating"}, {"type": "YA", "nodeID": "436", "text": "Asserting"}, {"type": "YA", "nodeID": "437", "text": "Default Illocuting"}, {"type": "YA", "nodeID": "438", "text": "Agreeing"}, {"type": "YA", "nodeID": "439", "text": "Disagreeing"}, {"type": "YA", "nodeID": "440", "text": "Agreeing"}, {"type": "YA", "nodeID": "441", "text": "Asserting"}, {"type": "YA", "nodeID": "442", "text": "Disagreeing"}, {"type": "YA", "nodeID": "443", "text": "Restating"}, {"type": "YA", "nodeID": "444", "text": "Disagreeing"}, {"type": "YA", "nodeID": "445", "text": "Disagreeing"}, {"type": "YA", "nodeID": "446", "text": "Asserting"}, {"type": "YA", "nodeID": "447", "text": "Disagreeing"}, {"type": "YA", "nodeID": "448", "text": "Asserting"}, {"type": "YA", "nodeID": "449", "text": "Disagreeing"}, {"type": "YA", "nodeID": "450", "text": "Rhetorical Questioning"}, {"type": "YA", "nodeID": "451", "text": "Restating"}, {"type": "YA", "nodeID": "452", "text": "Pure Questioning"}, {"type": "YA", "nodeID": "453", "text": "Restating"}], "edges": [{"edgeID": "0", "fromID": "0", "toID": "7"}, {"edgeID": "1", "fromID": "7", "toID": "1"}, {"edgeID": "2", "fromID": "1", "toID": "8"}, {"edgeID": "3", "fromID": "8", "toID": "2"}, {"edgeID": "4", "fromID": "2", "toID": "9"}, {"edgeID": "5", "fromID": "9", "toID": "3"}, {"edgeID": "6", "fromID": "3", "toID": "10"}, {"edgeID": "7", "fromID": "10", "toID": "4"}, {"edgeID": "8", "fromID": "4", "toID": "11"}, {"edgeID": "9", "fromID": "11", "toID": "5"}, {"edgeID": "10", "fromID": "5", "toID": "12"}, {"edgeID": "11", "fromID": "12", "toID": "6"}, {"edgeID": "12", "fromID": "13", "toID": "19"}, {"edgeID": "13", "fromID": "19", "toID": "14"}, {"edgeID": "14", "fromID": "14", "toID": "20"}, {"edgeID": "15", "fromID": "20", "toID": "15"}, {"edgeID": "16", "fromID": "15", "toID": "21"}, {"edgeID": "17", "fromID": "21", "toID": "16"}, {"edgeID": "18", "fromID": "16", "toID": "22"}, {"edgeID": "19", "fromID": "22", "toID": "17"}, {"edgeID": "20", "fromID": "17", "toID": "23"}, {"edgeID": "21", "fromID": "23", "toID": "18"}, {"edgeID": "22", "fromID": "0", "toID": "24"}, {"edgeID": "23", "fromID": "24", "toID": "13"}, {"edgeID": "24", "fromID": "18", "toID": "26"}, {"edgeID": "25", "fromID": "26", "toID": "25"}, {"edgeID": "26", "fromID": "18", "toID": "28"}, {"edgeID": "27", "fromID": "28", "toID": "27"}, {"edgeID": "28", "fromID": "18", "toID": "30"}, {"edgeID": "29", "fromID": "30", "toID": "29"}, {"edgeID": "30", "fromID": "18", "toID": "32"}, {"edgeID": "31", "fromID": "32", "toID": "31"}, {"edgeID": "32", "fromID": "18", "toID": "34"}, {"edgeID": "33", "fromID": "34", "toID": "33"}, {"edgeID": "34", "fromID": "35", "toID": "41"}, {"edgeID": "35", "fromID": "41", "toID": "36"}, {"edgeID": "36", "fromID": "36", "toID": "42"}, {"edgeID": "37", "fromID": "42", "toID": "37"}, {"edgeID": "38", "fromID": "37", "toID": "43"}, {"edgeID": "39", "fromID": "43", "toID": "38"}, {"edgeID": "40", "fromID": "38", "toID": "44"}, {"edgeID": "41", "fromID": "44", "toID": "39"}, {"edgeID": "42", "fromID": "39", "toID": "45"}, {"edgeID": "43", "fromID": "45", "toID": "40"}, {"edgeID": "44", "fromID": "0", "toID": "46"}, {"edgeID": "45", "fromID": "46", "toID": "35"}, {"edgeID": "46", "fromID": "40", "toID": "48"}, {"edgeID": "47", "fromID": "48", "toID": "47"}, {"edgeID": "48", "fromID": "40", "toID": "50"}, {"edgeID": "49", "fromID": "50", "toID": "49"}, {"edgeID": "50", "fromID": "40", "toID": "52"}, {"edgeID": "51", "fromID": "52", "toID": "51"}, {"edgeID": "52", "fromID": "53", "toID": "57"}, {"edgeID": "53", "fromID": "57", "toID": "54"}, {"edgeID": "54", "fromID": "54", "toID": "58"}, {"edgeID": "55", "fromID": "58", "toID": "55"}, {"edgeID": "56", "fromID": "55", "toID": "59"}, {"edgeID": "57", "fromID": "59", "toID": "56"}, {"edgeID": "58", "fromID": "0", "toID": "60"}, {"edgeID": "59", "fromID": "60", "toID": "53"}, {"edgeID": "60", "fromID": "56", "toID": "62"}, {"edgeID": "61", "fromID": "62", "toID": "61"}, {"edgeID": "62", "fromID": "56", "toID": "64"}, {"edgeID": "63", "fromID": "64", "toID": "63"}, {"edgeID": "64", "fromID": "56", "toID": "66"}, {"edgeID": "65", "fromID": "66", "toID": "65"}, {"edgeID": "66", "fromID": "56", "toID": "68"}, {"edgeID": "67", "fromID": "68", "toID": "67"}, {"edgeID": "68", "fromID": "56", "toID": "70"}, {"edgeID": "69", "fromID": "70", "toID": "69"}, {"edgeID": "70", "fromID": "71", "toID": "73"}, {"edgeID": "71", "fromID": "73", "toID": "72"}, {"edgeID": "72", "fromID": "0", "toID": "74"}, {"edgeID": "73", "fromID": "74", "toID": "71"}, {"edgeID": "74", "fromID": "72", "toID": "76"}, {"edgeID": "75", "fromID": "76", "toID": "75"}, {"edgeID": "76", "fromID": "72", "toID": "78"}, {"edgeID": "77", "fromID": "78", "toID": "77"}, {"edgeID": "78", "fromID": "72", "toID": "80"}, {"edgeID": "79", "fromID": "80", "toID": "79"}, {"edgeID": "80", "fromID": "72", "toID": "82"}, {"edgeID": "81", "fromID": "82", "toID": "81"}, {"edgeID": "82", "fromID": "72", "toID": "84"}, {"edgeID": "83", "fromID": "84", "toID": "83"}, {"edgeID": "84", "fromID": "85", "toID": "88"}, {"edgeID": "85", "fromID": "88", "toID": "86"}, {"edgeID": "86", "fromID": "86", "toID": "89"}, {"edgeID": "87", "fromID": "89", "toID": "87"}, {"edgeID": "88", "fromID": "4", "toID": "90"}, {"edgeID": "89", "fromID": "90", "toID": "85"}, {"edgeID": "90", "fromID": "87", "toID": "92"}, {"edgeID": "91", "fromID": "92", "toID": "91"}, {"edgeID": "92", "fromID": "87", "toID": "94"}, {"edgeID": "93", "fromID": "94", "toID": "93"}, {"edgeID": "94", "fromID": "87", "toID": "96"}, {"edgeID": "95", "fromID": "96", "toID": "95"}, {"edgeID": "96", "fromID": "97", "toID": "101"}, {"edgeID": "97", "fromID": "101", "toID": "98"}, {"edgeID": "98", "fromID": "98", "toID": "102"}, {"edgeID": "99", "fromID": "102", "toID": "99"}, {"edgeID": "100", "fromID": "99", "toID": "103"}, {"edgeID": "101", "fromID": "103", "toID": "100"}, {"edgeID": "102", "fromID": "4", "toID": "104"}, {"edgeID": "103", "fromID": "104", "toID": "97"}, {"edgeID": "104", "fromID": "100", "toID": "106"}, {"edgeID": "105", "fromID": "106", "toID": "105"}, {"edgeID": "106", "fromID": "100", "toID": "108"}, {"edgeID": "107", "fromID": "108", "toID": "107"}, {"edgeID": "108", "fromID": "100", "toID": "110"}, {"edgeID": "109", "fromID": "110", "toID": "109"}, {"edgeID": "110", "fromID": "100", "toID": "112"}, {"edgeID": "111", "fromID": "112", "toID": "111"}, {"edgeID": "112", "fromID": "113", "toID": "117"}, {"edgeID": "113", "fromID": "117", "toID": "114"}, {"edgeID": "114", "fromID": "114", "toID": "118"}, {"edgeID": "115", "fromID": "118", "toID": "115"}, {"edgeID": "116", "fromID": "115", "toID": "119"}, {"edgeID": "117", "fromID": "119", "toID": "116"}, {"edgeID": "118", "fromID": "4", "toID": "120"}, {"edgeID": "119", "fromID": "120", "toID": "113"}, {"edgeID": "120", "fromID": "116", "toID": "122"}, {"edgeID": "121", "fromID": "122", "toID": "121"}, {"edgeID": "122", "fromID": "116", "toID": "124"}, {"edgeID": "123", "fromID": "124", "toID": "123"}, {"edgeID": "124", "fromID": "116", "toID": "126"}, {"edgeID": "125", "fromID": "126", "toID": "125"}, {"edgeID": "126", "fromID": "127", "toID": "130"}, {"edgeID": "127", "fromID": "130", "toID": "128"}, {"edgeID": "128", "fromID": "128", "toID": "131"}, {"edgeID": "129", "fromID": "131", "toID": "129"}, {"edgeID": "130", "fromID": "4", "toID": "132"}, {"edgeID": "131", "fromID": "132", "toID": "127"}, {"edgeID": "132", "fromID": "129", "toID": "134"}, {"edgeID": "133", "fromID": "134", "toID": "133"}, {"edgeID": "134", "fromID": "129", "toID": "136"}, {"edgeID": "135", "fromID": "136", "toID": "135"}, {"edgeID": "136", "fromID": "129", "toID": "138"}, {"edgeID": "137", "fromID": "138", "toID": "137"}, {"edgeID": "138", "fromID": "129", "toID": "140"}, {"edgeID": "139", "fromID": "140", "toID": "139"}, {"edgeID": "140", "fromID": "129", "toID": "142"}, {"edgeID": "141", "fromID": "142", "toID": "141"}, {"edgeID": "142", "fromID": "143", "toID": "148"}, {"edgeID": "143", "fromID": "148", "toID": "144"}, {"edgeID": "144", "fromID": "144", "toID": "149"}, {"edgeID": "145", "fromID": "149", "toID": "145"}, {"edgeID": "146", "fromID": "145", "toID": "150"}, {"edgeID": "147", "fromID": "150", "toID": "146"}, {"edgeID": "148", "fromID": "146", "toID": "151"}, {"edgeID": "149", "fromID": "151", "toID": "147"}, {"edgeID": "150", "fromID": "5", "toID": "152"}, {"edgeID": "151", "fromID": "152", "toID": "143"}, {"edgeID": "152", "fromID": "147", "toID": "154"}, {"edgeID": "153", "fromID": "154", "toID": "153"}, {"edgeID": "154", "fromID": "147", "toID": "156"}, {"edgeID": "155", "fromID": "156", "toID": "155"}, {"edgeID": "156", "fromID": "147", "toID": "158"}, {"edgeID": "157", "fromID": "158", "toID": "157"}, {"edgeID": "158", "fromID": "159", "toID": "161"}, {"edgeID": "159", "fromID": "161", "toID": "160"}, {"edgeID": "160", "fromID": "5", "toID": "162"}, {"edgeID": "161", "fromID": "162", "toID": "159"}, {"edgeID": "162", "fromID": "160", "toID": "164"}, {"edgeID": "163", "fromID": "164", "toID": "163"}, {"edgeID": "164", "fromID": "160", "toID": "166"}, {"edgeID": "165", "fromID": "166", "toID": "165"}, {"edgeID": "166", "fromID": "160", "toID": "168"}, {"edgeID": "167", "fromID": "168", "toID": "167"}, {"edgeID": "168", "fromID": "169", "toID": "171"}, {"edgeID": "169", "fromID": "171", "toID": "170"}, {"edgeID": "170", "fromID": "5", "toID": "172"}, {"edgeID": "171", "fromID": "172", "toID": "169"}, {"edgeID": "172", "fromID": "170", "toID": "174"}, {"edgeID": "173", "fromID": "174", "toID": "173"}, {"edgeID": "174", "fromID": "170", "toID": "176"}, {"edgeID": "175", "fromID": "176", "toID": "175"}, {"edgeID": "176", "fromID": "170", "toID": "178"}, {"edgeID": "177", "fromID": "178", "toID": "177"}, {"edgeID": "178", "fromID": "170", "toID": "180"}, {"edgeID": "179", "fromID": "180", "toID": "179"}, {"edgeID": "180", "fromID": "181", "toID": "184"}, {"edgeID": "181", "fromID": "184", "toID": "182"}, {"edgeID": "182", "fromID": "182", "toID": "185"}, {"edgeID": "183", "fromID": "185", "toID": "183"}, {"edgeID": "184", "fromID": "5", "toID": "186"}, {"edgeID": "185", "fromID": "186", "toID": "181"}, {"edgeID": "186", "fromID": "183", "toID": "188"}, {"edgeID": "187", "fromID": "188", "toID": "187"}, {"edgeID": "188", "fromID": "183", "toID": "190"}, {"edgeID": "189", "fromID": "190", "toID": "189"}, {"edgeID": "190", "fromID": "191", "toID": "193"}, {"edgeID": "191", "fromID": "193", "toID": "192"}, {"edgeID": "192", "fromID": "6", "toID": "194"}, {"edgeID": "193", "fromID": "194", "toID": "191"}, {"edgeID": "194", "fromID": "192", "toID": "196"}, {"edgeID": "195", "fromID": "196", "toID": "195"}, {"edgeID": "196", "fromID": "192", "toID": "198"}, {"edgeID": "197", "fromID": "198", "toID": "197"}, {"edgeID": "198", "fromID": "199", "toID": "201"}, {"edgeID": "199", "fromID": "201", "toID": "200"}, {"edgeID": "200", "fromID": "6", "toID": "202"}, {"edgeID": "201", "fromID": "202", "toID": "199"}, {"edgeID": "202", "fromID": "200", "toID": "204"}, {"edgeID": "203", "fromID": "204", "toID": "203"}, {"edgeID": "204", "fromID": "200", "toID": "206"}, {"edgeID": "205", "fromID": "206", "toID": "205"}, {"edgeID": "206", "fromID": "200", "toID": "208"}, {"edgeID": "207", "fromID": "208", "toID": "207"}, {"edgeID": "208", "fromID": "200", "toID": "210"}, {"edgeID": "209", "fromID": "210", "toID": "209"}, {"edgeID": "210", "fromID": "200", "toID": "212"}, {"edgeID": "211", "fromID": "212", "toID": "211"}, {"edgeID": "212", "fromID": "213", "toID": "216"}, {"edgeID": "213", "fromID": "216", "toID": "214"}, {"edgeID": "214", "fromID": "214", "toID": "217"}, {"edgeID": "215", "fromID": "217", "toID": "215"}, {"edgeID": "216", "fromID": "6", "toID": "218"}, {"edgeID": "217", "fromID": "218", "toID": "213"}, {"edgeID": "218", "fromID": "215", "toID": "220"}, {"edgeID": "219", "fromID": "220", "toID": "219"}, {"edgeID": "220", "fromID": "215", "toID": "222"}, {"edgeID": "221", "fromID": "222", "toID": "221"}, {"edgeID": "222", "fromID": "215", "toID": "224"}, {"edgeID": "223", "fromID": "224", "toID": "223"}, {"edgeID": "224", "fromID": "215", "toID": "226"}, {"edgeID": "225", "fromID": "226", "toID": "225"}, {"edgeID": "226", "fromID": "227", "toID": "0"}, {"edgeID": "227", "fromID": "228", "toID": "1"}, {"edgeID": "228", "fromID": "229", "toID": "2"}, {"edgeID": "229", "fromID": "230", "toID": "3"}, {"edgeID": "230", "fromID": "231", "toID": "4"}, {"edgeID": "231", "fromID": "232", "toID": "5"}, {"edgeID": "232", "fromID": "233", "toID": "6"}, {"edgeID": "233", "fromID": "234", "toID": "7"}, {"edgeID": "234", "fromID": "235", "toID": "8"}, {"edgeID": "235", "fromID": "236", "toID": "9"}, {"edgeID": "236", "fromID": "237", "toID": "10"}, {"edgeID": "237", "fromID": "238", "toID": "11"}, {"edgeID": "238", "fromID": "239", "toID": "12"}, {"edgeID": "239", "fromID": "240", "toID": "13"}, {"edgeID": "240", "fromID": "241", "toID": "14"}, {"edgeID": "241", "fromID": "242", "toID": "15"}, {"edgeID": "242", "fromID": "243", "toID": "16"}, {"edgeID": "243", "fromID": "244", "toID": "17"}, {"edgeID": "244", "fromID": "245", "toID": "18"}, {"edgeID": "245", "fromID": "246", "toID": "19"}, {"edgeID": "246", "fromID": "247", "toID": "20"}, {"edgeID": "247", "fromID": "248", "toID": "21"}, {"edgeID": "248", "fromID": "249", "toID": "22"}, {"edgeID": "249", "fromID": "250", "toID": "23"}, {"edgeID": "250", "fromID": "251", "toID": "24"}, {"edgeID": "251", "fromID": "252", "toID": "25"}, {"edgeID": "252", "fromID": "253", "toID": "26"}, {"edgeID": "253", "fromID": "254", "toID": "27"}, {"edgeID": "254", "fromID": "255", "toID": "28"}, {"edgeID": "255", "fromID": "256", "toID": "29"}, {"edgeID": "256", "fromID": "257", "toID": "30"}, {"edgeID": "257", "fromID": "258", "toID": "31"}, {"edgeID": "258", "fromID": "259", "toID": "32"}, {"edgeID": "259", "fromID": "260", "toID": "33"}, {"edgeID": "260", "fromID": "261", "toID": "34"}, {"edgeID": "261", "fromID": "262", "toID": "35"}, {"edgeID": "262", "fromID": "263", "toID": "36"}, {"edgeID": "263", "fromID": "264", "toID": "37"}, {"edgeID": "264", "fromID": "265", "toID": "38"}, {"edgeID": "265", "fromID": "266", "toID": "39"}, {"edgeID": "266", "fromID": "267", "toID": "40"}, {"edgeID": "267", "fromID": "268", "toID": "41"}, {"edgeID": "268", "fromID": "269", "toID": "42"}, {"edgeID": "269", "fromID": "270", "toID": "43"}, {"edgeID": "270", "fromID": "271", "toID": "44"}, {"edgeID": "271", "fromID": "272", "toID": "45"}, {"edgeID": "272", "fromID": "273", "toID": "46"}, {"edgeID": "273", "fromID": "274", "toID": "47"}, {"edgeID": "274", "fromID": "275", "toID": "48"}, {"edgeID": "275", "fromID": "276", "toID": "49"}, {"edgeID": "276", "fromID": "277", "toID": "50"}, {"edgeID": "277", "fromID": "278", "toID": "51"}, {"edgeID": "278", "fromID": "279", "toID": "52"}, {"edgeID": "279", "fromID": "280", "toID": "53"}, {"edgeID": "280", "fromID": "281", "toID": "54"}, {"edgeID": "281", "fromID": "282", "toID": "55"}, {"edgeID": "282", "fromID": "283", "toID": "56"}, {"edgeID": "283", "fromID": "284", "toID": "57"}, {"edgeID": "284", "fromID": "285", "toID": "58"}, {"edgeID": "285", "fromID": "286", "toID": "59"}, {"edgeID": "286", "fromID": "287", "toID": "60"}, {"edgeID": "287", "fromID": "288", "toID": "61"}, {"edgeID": "288", "fromID": "289", "toID": "62"}, {"edgeID": "289", "fromID": "290", "toID": "63"}, {"edgeID": "290", "fromID": "291", "toID": "64"}, {"edgeID": "291", "fromID": "292", "toID": "65"}, {"edgeID": "292", "fromID": "293", "toID": "66"}, {"edgeID": "293", "fromID": "294", "toID": "67"}, {"edgeID": "294", "fromID": "295", "toID": "68"}, {"edgeID": "295", "fromID": "296", "toID": "69"}, {"edgeID": "296", "fromID": "297", "toID": "70"}, {"edgeID": "297", "fromID": "298", "toID": "71"}, {"edgeID": "298", "fromID": "299", "toID": "72"}, {"edgeID": "299", "fromID": "300", "toID": "73"}, {"edgeID": "300", "fromID": "301", "toID": "74"}, {"edgeID": "301", "fromID": "302", "toID": "75"}, {"edgeID": "302", "fromID": "303", "toID": "76"}, {"edgeID": "303", "fromID": "304", "toID": "77"}, {"edgeID": "304", "fromID": "305", "toID": "78"}, {"edgeID": "305", "fromID": "306", "toID": "79"}, {"edgeID": "306", "fromID": "307", "toID": "80"}, {"edgeID": "307", "fromID": "308", "toID": "81"}, {"edgeID": "308", "fromID": "309", "toID": "82"}, {"edgeID": "309", "fromID": "310", "toID": "83"}, {"edgeID": "310", "fromID": "311", "toID": "84"}, {"edgeID": "311", "fromID": "312", "toID": "85"}, {"edgeID": "312", "fromID": "313", "toID": "86"}, {"edgeID": "313", "fromID": "314", "toID": "87"}, {"edgeID": "314", "fromID": "315", "toID": "88"}, {"edgeID": "315", "fromID": "316", "toID": "89"}, {"edgeID": "316", "fromID": "317", "toID": "90"}, {"edgeID": "317", "fromID": "318", "toID": "91"}, {"edgeID": "318", "fromID": "319", "toID": "92"}, {"edgeID": "319", "fromID": "320", "toID": "93"}, {"edgeID": "320", "fromID": "321", "toID": "94"}, {"edgeID": "321", "fromID": "322", "toID": "95"}, {"edgeID": "322", "fromID": "323", "toID": "96"}, {"edgeID": "323", "fromID": "324", "toID": "97"}, {"edgeID": "324", "fromID": "325", "toID": "98"}, {"edgeID": "325", "fromID": "326", "toID": "99"}, {"edgeID": "326", "fromID": "327", "toID": "100"}, {"edgeID": "327", "fromID": "328", "toID": "101"}, {"edgeID": "328", "fromID": "329", "toID": "102"}, {"edgeID": "329", "fromID": "330", "toID": "103"}, {"edgeID": "330", "fromID": "331", "toID": "104"}, {"edgeID": "331", "fromID": "332", "toID": "105"}, {"edgeID": "332", "fromID": "333", "toID": "106"}, {"edgeID": "333", "fromID": "334", "toID": "107"}, {"edgeID": "334", "fromID": "335", "toID": "108"}, {"edgeID": "335", "fromID": "336", "toID": "109"}, {"edgeID": "336", "fromID": "337", "toID": "110"}, {"edgeID": "337", "fromID": "338", "toID": "111"}, {"edgeID": "338", "fromID": "339", "toID": "112"}, {"edgeID": "339", "fromID": "340", "toID": "113"}, {"edgeID": "340", "fromID": "341", "toID": "114"}, {"edgeID": "341", "fromID": "342", "toID": "115"}, {"edgeID": "342", "fromID": "343", "toID": "116"}, {"edgeID": "343", "fromID": "344", "toID": "117"}, {"edgeID": "344", "fromID": "345", "toID": "118"}, {"edgeID": "345", "fromID": "346", "toID": "119"}, {"edgeID": "346", "fromID": "347", "toID": "120"}, {"edgeID": "347", "fromID": "348", "toID": "121"}, {"edgeID": "348", "fromID": "349", "toID": "122"}, {"edgeID": "349", "fromID": "350", "toID": "123"}, {"edgeID": "350", "fromID": "351", "toID": "124"}, {"edgeID": "351", "fromID": "352", "toID": "125"}, {"edgeID": "352", "fromID": "353", "toID": "126"}, {"edgeID": "353", "fromID": "354", "toID": "127"}, {"edgeID": "354", "fromID": "355", "toID": "128"}, {"edgeID": "355", "fromID": "356", "toID": "129"}, {"edgeID": "356", "fromID": "357", "toID": "130"}, {"edgeID": "357", "fromID": "358", "toID": "131"}, {"edgeID": "358", "fromID": "359", "toID": "132"}, {"edgeID": "359", "fromID": "360", "toID": "133"}, {"edgeID": "360", "fromID": "361", "toID": "134"}, {"edgeID": "361", "fromID": "362", "toID": "135"}, {"edgeID": "362", "fromID": "363", "toID": "136"}, {"edgeID": "363", "fromID": "364", "toID": "137"}, {"edgeID": "364", "fromID": "365", "toID": "138"}, {"edgeID": "365", "fromID": "366", "toID": "139"}, {"edgeID": "366", "fromID": "367", "toID": "140"}, {"edgeID": "367", "fromID": "368", "toID": "141"}, {"edgeID": "368", "fromID": "369", "toID": "142"}, {"edgeID": "369", "fromID": "370", "toID": "143"}, {"edgeID": "370", "fromID": "371", "toID": "144"}, {"edgeID": "371", "fromID": "372", "toID": "145"}, {"edgeID": "372", "fromID": "373", "toID": "146"}, {"edgeID": "373", "fromID": "374", "toID": "147"}, {"edgeID": "374", "fromID": "375", "toID": "148"}, {"edgeID": "375", "fromID": "376", "toID": "149"}, {"edgeID": "376", "fromID": "377", "toID": "150"}, {"edgeID": "377", "fromID": "378", "toID": "151"}, {"edgeID": "378", "fromID": "379", "toID": "152"}, {"edgeID": "379", "fromID": "380", "toID": "153"}, {"edgeID": "380", "fromID": "381", "toID": "154"}, {"edgeID": "381", "fromID": "382", "toID": "155"}, {"edgeID": "382", "fromID": "383", "toID": "156"}, {"edgeID": "383", "fromID": "384", "toID": "157"}, {"edgeID": "384", "fromID": "385", "toID": "158"}, {"edgeID": "385", "fromID": "386", "toID": "159"}, {"edgeID": "386", "fromID": "387", "toID": "160"}, {"edgeID": "387", "fromID": "388", "toID": "161"}, {"edgeID": "388", "fromID": "389", "toID": "162"}, {"edgeID": "389", "fromID": "390", "toID": "163"}, {"edgeID": "390", "fromID": "391", "toID": "164"}, {"edgeID": "391", "fromID": "392", "toID": "165"}, {"edgeID": "392", "fromID": "393", "toID": "166"}, {"edgeID": "393", "fromID": "394", "toID": "167"}, {"edgeID": "394", "fromID": "395", "toID": "168"}, {"edgeID": "395", "fromID": "396", "toID": "169"}, {"edgeID": "396", "fromID": "397", "toID": "170"}, {"edgeID": "397", "fromID": "398", "toID": "171"}, {"edgeID": "398", "fromID": "399", "toID": "172"}, {"edgeID": "399", "fromID": "400", "toID": "173"}, {"edgeID": "400", "fromID": "401", "toID": "174"}, {"edgeID": "401", "fromID": "402", "toID": "175"}, {"edgeID": "402", "fromID": "403", "toID": "176"}, {"edgeID": "403", "fromID": "404", "toID": "177"}, {"edgeID": "404", "fromID": "405", "toID": "178"}, {"edgeID": "405", "fromID": "406", "toID": "179"}, {"edgeID": "406", "fromID": "407", "toID": "180"}, {"edgeID": "407", "fromID": "408", "toID": "181"}, {"edgeID": "408", "fromID": "409", "toID": "182"}, {"edgeID": "409", "fromID": "410", "toID": "183"}, {"edgeID": "410", "fromID": "411", "toID": "184"}, {"edgeID": "411", "fromID": "412", "toID": "185"}, {"edgeID": "412", "fromID": "413", "toID": "186"}, {"edgeID": "413", "fromID": "414", "toID": "187"}, {"edgeID": "414", "fromID": "415", "toID": "188"}, {"edgeID": "415", "fromID": "416", "toID": "189"}, {"edgeID": "416", "fromID": "417", "toID": "190"}, {"edgeID": "417", "fromID": "418", "toID": "191"}, {"edgeID": "418", "fromID": "419", "toID": "192"}, {"edgeID": "419", "fromID": "420", "toID": "193"}, {"edgeID": "420", "fromID": "421", "toID": "194"}, {"edgeID": "421", "fromID": "422", "toID": "195"}, {"edgeID": "422", "fromID": "423", "toID": "196"}, {"edgeID": "423", "fromID": "424", "toID": "197"}, {"edgeID": "424", "fromID": "425", "toID": "198"}, {"edgeID": "425", "fromID": "426", "toID": "199"}, {"edgeID": "426", "fromID": "427", "toID": "200"}, {"edgeID": "427", "fromID": "428", "toID": "201"}, {"edgeID": "428", "fromID": "429", "toID": "202"}, {"edgeID": "429", "fromID": "430", "toID": "203"}, {"edgeID": "430", "fromID": "431", "toID": "204"}, {"edgeID": "431", "fromID": "432", "toID": "205"}, {"edgeID": "432", "fromID": "433", "toID": "206"}, {"edgeID": "433", "fromID": "434", "toID": "207"}, {"edgeID": "434", "fromID": "435", "toID": "208"}, {"edgeID": "435", "fromID": "436", "toID": "209"}, {"edgeID": "436", "fromID": "437", "toID": "210"}, {"edgeID": "437", "fromID": "438", "toID": "211"}, {"edgeID": "438", "fromID": "439", "toID": "212"}, {"edgeID": "439", "fromID": "440", "toID": "213"}, {"edgeID": "440", "fromID": "441", "toID": "214"}, {"edgeID": "441", "fromID": "442", "toID": "215"}, {"edgeID": "442", "fromID": "443", "toID": "216"}, {"edgeID": "443", "fromID": "444", "toID": "217"}, {"edgeID": "444", "fromID": "445", "toID": "218"}, {"edgeID": "445", "fromID": "446", "toID": "219"}, {"edgeID": "446", "fromID": "447", "toID": "220"}, {"edgeID": "447", "fromID": "448", "toID": "221"}, {"edgeID": "448", "fromID": "449", "toID": "222"}, {"edgeID": "449", "fromID": "450", "toID": "223"}, {"edgeID": "450", "fromID": "451", "toID": "224"}, {"edgeID": "451", "fromID": "452", "toID": "225"}, {"edgeID": "452", "fromID": "453", "toID": "226"}]}